{
  "products": [
    {
      "name": "Jugo de Zanahoria",
      "price": 31,
      "id": 1
    },
    {
      "id": 2,
      "name": "Jugo de Naranja",
      "price": "1"
    },
    {
      "name": "Jugo de Naranja",
      "price": "300",
      "id": 3
    },
    {
      "name": "Rib Eye 800g",
      "price": "200",
      "id": 4
    },
    {
      "name": "Jugo de Fresa",
      "price": "200",
      "id": 5
    },
    {
      "name": "a",
      "price": 1,
      "id": 6
    },
    {
      "name": "12321",
      "price": 123,
      "id": 7
    },
    {
      "name": "12321",
      "price": 123,
      "id": 8
    },
    {
      "name": "Hola",
      "price": 1234,
      "id": 9
    },
    {
      "name": "Sal",
      "price": 3,
      "id": 10
    }
  ]
}